pytchout/__init__.py
pytchout/analysis/arsenal.py
pytchout/fangraphs.py
pytchout/misc.py
pytchout/request.py
pytchout/retrosheet.py
pytchout/similarity.py
pytchout/statcast.py
pytchout/tools/nathan.py
pytchout/utils.py
pytchout/visualization.py
pytchout-0.1.0.dist-info/LICENSE
pytchout-0.1.0.dist-info/WHEEL
pytchout-0.1.0.dist-info/METADATA
pytchout-0.1.0.dist-info/RECORD
